Workbook

Sheet Summary
A1: Grab DCF model
A2: Share price $3.07 as of the 6th of October 2026, units in ($m) unless stated otherwise
A3: Colour key: blue = typed input, black = formula, green = link to another tab
A5: Key assumptions
A6: WACC | B6: =WACC!B19 -> 0.11575431
A7: Cost of equity | B7: =WACC!B8 -> 0.12529
A8: Risk-free rate | B8: =WACC!B4 -> 0.0531
A9: Beta | B9: =WACC!B7 -> 1.3
A10: Terminal growth rate | B10: =DCF!B10 -> 0.025
A11: Tax rate | B11: =Forecast!C10 -> 0.22
A12: Deliveries growth, FY26E | B12: =Forecast!C6 -> 0.21
A13: Deliveries growth, FY35E | B13: =Forecast!L6 -> 0.05
A14: Mobility growth, FY26E | B14: =Forecast!C7 -> 0.13
A15: Mobility growth, FY35E | B15: =Forecast!L7 -> 0.05
A16: Financial services growth, FY26E | B16: =Forecast!C8 -> 0.6
A17: Financial services growth, FY35E | B17: =Forecast!L8 -> 0.05
A18: Operating margin (after SBC) FY26E | B18: =Forecast!C9 -> 0.04
A19: Operating margin (after SBC) FY35E | B19: =Forecast!L9 -> 0.15
A20: Share price used | B20: =WACC!B14 -> 3.07
A22: Sources
A23: Grab Holdings Form 20-F for FY2024 and FY2025 (historical financials, segment revenue, share counts, debt note).
A24: Grab quarterly earnings press releases: Q3 2025, Q4 2025, Q1 2026, Q2 2026 (LTM figures, Jun-26 balance sheet, guidance).
A25: Damodaran (NYU Stern), January 2026 data: equity risk premium, country risk premiums, industry betas.
A26: US Treasury 10-year yield, 5 Oct 2026 (FRED / Federal Reserve H.15).
A27: Grab share price (GRAB), closing price on 6 Oct 2026.
A29: Known limitations
A30: The forecast is deliberately cautious. FY26E and FY28E are below management’s guidance and its $1.5bn adjusted EBITDA target, because the model uses operating profit after share-based pay and not adjusted EBITDA.
A31: FY26 cash flows are discounted as if they were a full year ahead despite it being October. Using the Jun-26 balance sheet against an October share price adds a small timing mismatch.
A32: The banking loan book isn't forecast or valued, although customer deposits are deducted making the result slightly conservative.
A33: Diluted shares are approximated by the Q2 2026 diluted weighted average (4,168m). Options, RSUs and July buybacks aren’t separately modelled.
A34: Tax is a flat 22% blended rate. Tax-loss carry-forwards are ignored.
... A37: Cost of debt uses a risk-free-plus-2% credit spread. Grab’s credit rating wasn’t checked.

Sheet Historicals
A1: ($m) | B1: FY23 | C1: FY24 | D1: FY25 | E1: H1 25 | F1: H1 26 | G1: LTM Jun-26 | H1: Source/Notes | J1: Blue = typed from reports, black = formula
A2: Revenue | H2: FY23 as recast in later reports | J2: Units: $m unless stated; shares in millions; liquidity memo in $bn
A3: Deliveries | B3: 1310 | C3: 1493 | D3: 1800 | E3: 854 | F3: 1041 | G3: =D3+F3-E3 -> 1987 | H3: FY23-FY25: FY25 20-F, Note 19 Revenue streams (p.F-53). H1 25 and H1 26: Q1 + Q2 from the Q1-26 (5 May 2026) and Q2-26 (4 Aug 2026) press releases, segment tables. LTM = FY25 + H1 26 - H1 25.
A4: Mobility | B4: 871 | C4: 1047 | D4: 1219 | E4: 577 | F4: 668 | G4: =D4+F4-E4 -> 1310 | H4: FY23-FY25: FY25 20-F, Note 19 Revenue streams (p.F-53). H1 25 and H1 26: Q1 + Q2 from the Q1-26 and Q2-26 press releases, segment tables. LTM = FY25 + H1 26 - H1 25.
A5: Financial services | B5: 177 | C5: 253 | D5: 347 | E5: 159 | F5: 241 | G5: =D5+F5-E5 -> 429 | H5: FY23-FY25: FY25 20-F, Note 19 Revenue streams (p.F-53). H1 25 and H1 26: Q1 + Q2 from the Q1-26 and Q2-26 press releases, segment tables. H1 26 and LTM include Superbank from June 2026, so not like-for-like with earlier periods.
A6: Others | B6: 1 | C6: 4 | D6: 4 | E6: 2 | F6: 2 | G6: =D6+F6-E6 -> 4 | H6: FY23-FY25: FY25 20-F, Note 19 Revenue streams (p.F-53). H1 25 and H1 26: Q1 + Q2 from the Q1-26 and Q2-26 press releases, segment tables. Small amounts, rounded to $1m.
A7: Total revenue | B7: =SUM(B3:B6) -> 2359 | C7: =SUM(C3:C6) -> 2797 | D7: =SUM(D3:D6) -> 3370 | E7: =SUM(E3:E6) -> 1592 | F7: =SUM(F3:F6) -> 1952 | G7: =SUM(G3:G6) -> 3730 | H7: Sum of above four segments
A8: Reported Total | B8: 2359 | C8: 2797 | D8: 3370 | E8: 1592 | F8: 1953 | G8: =D8+F8-E8 -> 3731 | H8: FY23-FY25: FY25 20-F, Note 19 total (p.F-53). H1 25 and H1 26: six-month revenue in the Q2-26 press release income statement. LTM = FY25 + H1 26 - H1 25.
A9: Check | B9: =B7-B8 -> 0 | C9: =C7-C8 -> 0 | D9: =D7-D8 -> 0 | E9: =E7-E8 -> 0 | F9: =F7-F8 -> -1 | G9: =G7-G8 -> -1 | H9: Total revenue minus reported total. H1 26 segments sum to 1,952 vs 1,953 reported (rounding); the LTM column carries the same -1.
A10: Growth % | C10: =C7/B7-1 -> 0.18567189 | D10: =D7/C7-1 -> 0.20486235 | F10: =F7/E7-1 -> 0.22613065 | H10: Year-on-year change. FY23 growth not shown (FY22 not in this model). H1 26 growth is vs H1 25.
A11: ($m)
A12: Profit and adjusted EBITDA bridge
A13: Operating profit/(loss) | B13: -519 | C13: -168 | D13: 65 | E13: -14 | F13: 41 | G13: =D13+F13-E13 -> 120 | H13: FY23: FY24 20-F, Adjusted EBITDA reconciliation (p.137), 2023 as recast. FY24-FY25: Q4-25 press release (12 Feb 2026) and FY25 20-F reconciliation. H1 25 and H1 26: Q2-26 press release (4 Aug 2026), six-month columns. LTM = FY25 + H1 26 - H1 25.
A14: Net other (Income)/expense | B14: -17 | C14: -13 | D14: -12 | E14: -10 | F14: -1 | G14: =D14+F14-E14 -> -3 | H14: Same sources as operating profit. Sign follows Grab's reconciliation: negative = other income, which is deducted when moving from operating profit to adjusted EBITDA.
A15: Depreciation & Amortization | B15: 145 | C15: 147 | D15: 177 | E15: 81 | F15: 109 | G15: =D15+F15-E15 -> 205 | H15: Same sources as operating profit. Non-cash, added back in Grab's adjusted EBITDA.
A16: Share-based compensation | B16: 304 | C16: 279 | D16: 241 | E16: 141 | F16: 140 | G16: =D16+F16-E16 -> 240 | H16: Same sources as operating profit. Non-cash, but a real cost to shareholders through dilution. Excluded from Grab's adjusted EBITDA; treated as a cost in my DCF.
A17: M&A costs | B17: 0 | C17: 6 | D17: 20 | E17: 6 | F17: 7 | G17: =D17+F17-E17 -> 21 | H17: FY24 onwards: Q4-25 press release and Q2-26 press release. FY23 shown as 0 because FY23 M&A costs were not split out in the FY24 20-F; they sit inside the legal, tax and regulatory provisions line. Grab began showing M&A costs separately from Q1 2025 and re-presented FY24 (FY24 20-F showed 54 combined; later reports show 6 M&A + 48 legal).
A18: Day-1 credit loss on acquired loans | B18: 0 | C18: 0 | D18: 0 | E18: 0 | F18: 15 | G18: =D18+F18-E18 -> 15 | H18: New reconciling item from Q2-26 press release (4 Aug 2026): day-1 expected credit loss on an acquired loan portfolio, $15m. Not present in earlier periods, so FY23-H1 25 = 0.
A19: Restructuring costs | B19: 56 | C19: 14 | D19: 12 | E19: 3 | F19: 6 | G19: =D19+F19-E19 -> 15 | H19: Same sources as operating profit.
A20: Legal, tax & regulatory provisions | B20: 9 | C20: 48 | D20: -3 | E20: 8 | F20: 6 | G20: =D20+F20-E20 -> -5 | H20: Same sources as operating profit. Negative = net release/reversal of provisions (FY25 and LTM), which reduces adjusted EBITDA. FY24 is 48 on the re-presented basis (54 as originally reported, including 6 M&A costs).
A21: ($m)
A22: Adjusted EBITDA (reported) | B22: -22 | C22: 313 | D22: 500 | E22: 215 | F22: 323 | G22: =D22+F22-E22 -> 608 | H22: Non-IFRS measure as reported by Grab: profit adjusted for finance items, tax, D&A, share-based compensation, M&A, impairment, restructuring, legal provisions and other items. FY23 as recast in FY24 20-F. Check row confirms the lines above sum to this.
A23: Regional Corporate costs | B23: 398 | C23: 350 | D23: 368 | E23: 178 | F23: 217 | G23: =D23+F23-E23 -> 407 | H23: Costs not attributed to any segment (central cloud/tech, R&D, G&A, marketing). Excludes share-based compensation and capitalised software. Same sources as the adjusted EBITDA reconciliation: FY23 FY24 20-F (recast); FY24-FY25 Q4-25 press release; H1 25 and H1 26 Q2-26 press release. Entered as a positive cost. Grew in H1 26 on staff, cloud and software costs.
A24: ($m)
A25: Total segment adj. EBITDA | B25: 376 | C25: 663 | D25: 868 | E25: 393 | F25: 540 | G25: =D25+F25-E25 -> 1015 | H25: Sum of the four segment adjusted EBITDA figures, before regional corporate costs. Same sources as above. Total segment adj. EBITDA minus regional corporate costs = adjusted EBITDA.
A26: Deliveries | B26: 81 | C26: 196 | D26: 287 | E26: 126 | F26: 184 | G26: =D26+F26-E26 -> 345 | H26: Segment adjusted EBITDA from the reconciliation in the sources above. Margin is measured against Deliveries GMV in Grab's reports, not revenue.
A27: Mobility | B27: 466 | C27: 569 | D27: 690 | E27: 323 | F27: 389 | G27: =D27+F27-E27 -> 756 | H27: Segment adjusted EBITDA from the reconciliation in the sources above. Grab's most profitable segment. Margin is measured against Mobility GMV in Grab's reports.
A28: Financial Services | B28: -170 | C28: -105 | D28: -110 | E28: -56 | F28: -32 | G28: =D28+F28-E28 -> -86 | H28: Segment adjusted EBITDA from the reconciliation in the sources above. H1 26 and LTM include Superbank from June 2026 (not like-for-like with earlier periods). Loss reflects credit loss provisions as the loan book scales.
A29: Others | B29: -1 | C29: 3 | D29: 1 | E29: 0 | F29: -1 | G29: =D29+F29-E29 -> 0 | H29: Segment adjusted EBITDA from the reconciliation in the sources above. Small amounts.
A30: Bridge Check | B30: =SUM(B13:B20)-B22 -> 0 | C30: =SUM(C13:C20)-C22 -> 0 | D30: =SUM(D13:D20)-D22 -> 0 | E30: =SUM(E13:E20)-E22 -> 0 | F30: =SUM(F13:F20)-F22 -> 0 | G30: =SUM(G13:G20)-G22 -> 0 | H30: Operating profit plus all add-backs, minus reported adjusted EBITDA. Should be 0. Impairment (under $1m in every period) is excluded.
A31: Segment Check | B31: =SUM(B26:B29) - B25 -> 0 | C31: =SUM(C26:C29) - C25 -> 0 | D31: =SUM(D26:D29) - D25 -> 0 | E31: =SUM(E26:E29) - E25 -> 0 | F31: =SUM(F26:F29) - F25 -> 0 | G31: =SUM(G26:G29) - G25 -> 0 | H31: Sum of the four segment adjusted EBITDA lines, minus reported total segment adjusted EBITDA. Should be 0.
A32: Corporate Check | B32: =B25-B23-B22 -> 0 | C32: =C25-C23-C22 -> 0 | D32: =D25-D23-D22 -> 0 | E32: =E25-E23-E22 -> 0 | F32: =F25-F23-F22 -> 0 | G32: =G25-G23-G22 -> 0 | H32: Total segment adjusted EBITDA, minus regional corporate costs, minus reported adjusted EBITDA. Should be 0.
A35: ($m) | B35: Dec-23 | C35: Dec-24 | D35: Dec-25 | E35: Jun-26 | H35: Source/Notes
A36: Balance sheet | H36: Period-end snapshots, so no LTM column. Figures entered as reported, with no adjustments. FY24 20-F = Form 20-F for the year ended 31 Dec 2024; FY25 20-F = Form 20-F for the year ended 31 Dec 2025. Page references give the printed page and then the PDF page; the press releases have no printed page numbers, so PDF page only.
A37: Cash and cash equivalents | B37: 3138 | C37: 2964 | D37: 3433 | E37: 2859 | H37: Dec-23 and Dec-24: FY24 20-F, consolidated statement of financial position (p.F-5, PDF p.194). Dec-25: FY25 20-F, consolidated statement of financial position (p.F-5, PDF p.149); same figure in the Q4-25 press release (PDF p.19). Jun-26: Q2-26 press release (4 Aug 2026), condensed statement of financial position (PDF p.15). Current assets.
A38: Other investments - current | B38: 1905 | C38: 2665 | D38: 3371 | E38: 3441 | H38: Dec-23 and Dec-24: FY24 20-F, consolidated statement of financial position (p.F-5, PDF p.194). Dec-25: FY25 20-F, consolidated statement of financial position (p.F-5, PDF p.149); same figure in the Q4-25 press release (PDF p.19). Jun-26: Q2-26 press release (4 Aug 2026), condensed statement of financial position (PDF p.15). "Other investments" line under current assets.
A39: Other investments - non-current | B39: 1188 | C39: 765 | D39: 1023 | E39: 1476 | H39: Dec-23 and Dec-24: FY24 20-F, consolidated statement of financial position (p.F-5, PDF p.194). Dec-25: FY25 20-F, consolidated statement of financial position (p.F-5, PDF p.149); same figure in the Q4-25 press release (PDF p.18). Jun-26: Q2-26 press release (4 Aug 2026), condensed statement of financial position (PDF p.15). "Other investments" line under non-current assets.
A40: Loans & borrowings - non-current | B40: 668 | C40: 241 | D40: 373 | E40: 409 | H40: Dec-23 and Dec-24: FY24 20-F, consolidated statement of financial position (p.F-5, PDF p.194). Dec-25: FY25 20-F, consolidated statement of financial position (p.F-5, PDF p.149); same figure in the Q4-25 press release (PDF p.19). Jun-26: Q2-26 press release (4 Aug 2026), condensed statement of financial position (PDF p.16). "Loans and borrowings" line under non-current liabilities. Includes lease liabilities (FY24 20-F Note 14, p.F-42; FY25 20-F Note 13, p.F-41).
A41: Loans & borrowings - current | B41: 125 | C41: 123 | D41: 1680 | E41: 1624 | H41: Dec-23 and Dec-24: FY24 20-F, consolidated statement of financial position (p.F-5, PDF p.194). Dec-25: FY25 20-F, consolidated statement of financial position (p.F-5, PDF p.149); same figure in the Q4-25 press release (PDF p.19). Jun-26: Q2-26 press release (4 Aug 2026), condensed statement of financial position (PDF p.16). "Loans and borrowings" line under current liabilities. Includes lease liabilities and, at Dec-25, the convertible notes (FY25 20-F Note 13, p.F-41).
A42: of which convertible notes | B42: 0 | C42: 0 | D42: 1502 | H42: Dec-25: FY25 20-F, Note 13 Loans and borrowings, "Convertible notes (including embedded derivative)" = 1,502, shown within current (p.F-41, PDF p.185). Per Note 13(ii) this is a host liability of 1,042 plus an embedded derivative of 460; principal is 1,500 (p.F-43, PDF p.187). Dec-23 and Dec-24: the FY24 20-F Note 14 (p.F-42, PDF p.231) has no convertible notes line; the FY25 20-F indebtedness table reports "-" for both 2024 and 2023 (p.102, PDF p.105), so 0 is entered as reported. Jun-26: not disclosed in the Q2-26 press release. The Q2-26 press release shows loans and borrowings as two lines only and does not split out the convertible notes, so the cell is left blank.
A43: Customer deposits (banking) | B43: 374 | C43: 1225 | D43: 1629 | E43: 2513 | H43: Dec-23 and Dec-24: FY24 20-F, consolidated statement of financial position (p.F-5, PDF p.194). Dec-25: FY25 20-F, consolidated statement of financial position (p.F-5, PDF p.149); same figure in the Q4-25 press release (PDF p.19). Jun-26: Q2-26 press release (4 Aug 2026), condensed statement of financial position (PDF p.16). Reported caption: "Deposits from customers in the banking business", all within current liabilities.
A44: Non-controlling interests | B44: 19 | C44: -48 | D44: 29 | E44: 437 | H44: Dec-23 and Dec-24: FY24 20-F, consolidated statement of financial position (p.F-5, PDF p.194). Dec-25: FY25 20-F, consolidated statement of financial position (p.F-5, PDF p.149); same figure in the Q4-25 press release (PDF p.19). Jun-26: Q2-26 press release (4 Aug 2026), condensed statement of financial position (PDF p.16). Within equity. Dec-24 is negative as reported: (48).
A45: Total equity | B45: 6468 | C45: 6351 | D45: 6757 | E45: 7203 | H45: Dec-23 and Dec-24: FY24 20-F, consolidated statement of financial position (p.F-5, PDF p.194). Dec-25: FY25 20-F, consolidated statement of financial position (p.F-5, PDF p.149); same figure in the Q4-25 press release (PDF p.19). Jun-26: Q2-26 press release (4 Aug 2026), condensed statement of financial position (PDF p.16). Reported "Total equity", which includes non-controlling interests.
A46: Total loans & borrowings | B46: =B40+B41 -> 793 | C46: =C40+C41 -> 364 | D46: =D40+D41 -> 2053 | E46: =E40+E41 -> 2033 | H46: Non-current plus current loans and borrowings.
A47: Reported loans & borrowings | B47: 793 | C47: 364 | D47: 2053 | H47: Total carrying amount in the terms and debt repayment schedule. Dec-23 (793) and Dec-24 (364): FY24 20-F, Note 14(i) (p.F-43, PDF p.232). Dec-25 (2,053): FY25 20-F, Note 13(i) (p.F-42, PDF p.186). Jun-26: not disclosed in the Q2-26 press release. The Q2-26 press release has no loans and borrowings note or total, so the cell is left blank.
A48: Check | B48: =IF(ISNUMBER(B47),B46-B47,"n/a") -> 0 | C48: =IF(ISNUMBER(C47),C46-C47,"n/a") -> 0 | D48: =IF(ISNUMBER(D47),D46-D47,"n/a") -> 0 | E48: =IF(ISNUMBER(E47),E46-E47,"n/a") -> n/a | H48: Total loans and borrowings minus the reported total. Should be 0. Jun-26 shows n/a because there is no reported total to check against.
A50: Memo Items
A51: Lease liabilities within borrowings ($m) | C51: 158 | D51: 234 | H51: Memo Only: Lease liabilities already included in total loans and borrowings above (non-current + current); do not add again. Dec-24 (125 + 33) and Dec-25 (185 + 49): FY25 20-F, Note 13 Loans and borrowings. Dec-23: FY24 20-F debt note, not entered. Jun-26: not in the Q2-26 press release
A52: Gross cash liquidity, reported ($bn) | C52: 6.1 | D52: 7.4 | E52: 7.4 | H52: Grab's non-IFRS measure, reported in $bn (rounded): cash on hand, short and long-term time deposits, marketable securities and restricted cash. Dec-24 and Dec-25: Q4-25 press release. Jun-26: Q2-26 press release. Dec-23 not entered.
A53: Net cash liquidity, reported ($bn) | D53: 5.4 | E53: 5.4 | H53: Grab's non-IFRS measure: gross cash liquidity less loans and borrowings, in $bn (rounded). Dec-25: Q4-25 press release. Jun-26: Q2-26 press release. Dec-24 and Dec-23 not entered. Includes cash that backs customer deposits.
A55: (millions) | B55: Dec-23 | C55: Dec-24 | D55: Dec-25 | E55: Jun-26 | H55: Source/Notes
A56: Shares | H56: Period-end share counts. The 20-Fs report in thousands of shares; entered here in millions. Jun-26 figures come from a sentence in the Q2-26 press release and are given to the nearest million only.
A57: Class A shares outstanding | B57: 3813.341 | C57: 3950.499 | D57: 3969.291 | E57: 3974 | H57: Dec-23 (3,813,341 thousand) and Dec-24 (3,950,499 thousand): FY24 20-F, Note 12(i) Share capital and share premium, "In issue at December 31 - fully paid" (p.F-40, PDF p.229). Dec-25 (3,969,291 thousand): FY25 20-F, Note 11(i) (p.F-39, PDF p.183); the Q4-25 press release gives 3,969 million (PDF p.18). Jun-26: Q2-26 press release, 3,974 million (PDF p.15).
A58: Class B shares outstanding | B58: 110.066 | C58: 114.879 | D58: 120.194 | E58: 105 | H58: Same sources and pages as Class A. Dec-23 110,066, Dec-24 114,879 and Dec-25 120,194 thousand are the "In issue at December 31 - fully paid" line. This is the basis the press releases call "outstanding" (115 million at Dec-24 and 120 million at Dec-25, Q4-25 press release PDF p.18) and the only basis reported for Jun-26 (105 million, Q2-26 press release PDF p.15). The 20-Fs also report Class B "In issue at December 31" before deducting restricted shares issued but not fully vested: 120,403 (Dec-23), 119,799 (Dec-24) and 128,356 (Dec-25) thousand; the 20-F cover pages use that higher figure. Not used here, so the row is on one basis across all four dates.
A59: Total outstanding | B59: =B57+B58 -> 3923.407 | C59: =C57+C58 -> 4065.378 | D59: =D57+D58 -> 4089.485 | E59: =E57+E58 -> 4079 | H59: Class A plus Class B. The files give no reported total at these dates, so there is no check row.
A60: Potentially dilutive securities excluded from diluted EPS (bases differ, see note) | B60: 343.035 | C60: 222.491 | D60: 269.026 | E60: 518 | H60: Dec-23 (343,035 thousand) and Dec-24 (222,491 thousand): FY24 20-F, Note 23 Loss per share, total of potentially dilutive outstanding securities excluded from diluted loss per share (p.F-56, PDF p.245). Dec-25 (269,026 thousand): FY25 20-F, Note 22(ii), same table (p.F-56, PDF p.200); the Q4-25 press release gives 269 million (PDF p.18). The Dec-25 total includes 229,008 thousand for the convertible notes and is the securities EXCLUDED from diluted EPS; a further 113,934 thousand (options 10,259, RSUs and restricted shares 101,947, ESPP 1,728) was included in the FY25 diluted weighted average and is not in this figure. Jun-26: Q2-26 press release (PDF p.15) says 518 million potentially dilutive securities "have been considered for the computation of diluted earnings per ordinary share for the three months ended June 30, 2026". No breakdown is given, and it relates to the quarter rather than a 30 June balance, so it may not be like-for-like with the 20-F figures.
A62: (millions) | B62: FY23 | C62: FY24 | D62: FY25 | E62: H1 25 | F62: H1 26 | H62: Source/Notes
A63: Weighted-average shares | H63: Weighted-average ordinary shares outstanding used for earnings per share. Reported in thousands; entered in millions. No LTM column and no check row: the files give nothing further to tie these to.
A64: Basic | B64: 3894.724 | C64: 3995.237 | D64: 4092.151 | E64: 4099.96 | F64: 4088.747 | H64: FY23 (3,894,724 thousand) and FY24 (3,995,237 thousand): FY24 20-F, Note 23 Loss per share (p.F-56, PDF p.245). FY25 (4,092,151 thousand): FY25 20-F, Note 22(i) (p.F-55, PDF p.199); same in the Q4-25 press release (PDF p.18). H1 25 (4,099,960 thousand) and H1 26 (4,088,747 thousand): Q2-26 press release, six months ended June 30 columns (PDF p.15).
A65: Diluted | B65: 3894.724 | C65: 3995.237 | D65: 4206.085 | E65: 4201.469 | F65: 4398.185 | H65: FY23 and FY24: the FY24 20-F Note 23 (p.F-56, PDF p.245) prints no separate diluted share count and states that basic and diluted loss per share were the same because of the loss. The FY25 20-F, Note 22(ii) prints the diluted weighted average for 2023 and 2024 as 3,894,724 and 3,995,237 thousand, equal to basic (p.F-56, PDF p.200); those are the figures entered. FY25 (4,206,085 thousand): same table; same in the Q4-25 press release (PDF p.18). H1 25 (4,201,469 thousand) and H1 26 (4,398,185 thousand): Q2-26 press release, six months ended June 30 columns (PDF p.15).
A67: ($M) | B67: FY23 | C67: FY24 | D67: FY25 | E67: H1 25 | F67: H1 26 | G67: LTM Jun-26
A68: Cash Flow
A69: Operating cash flow | B69: 86 | C69: 852 | D69: 79 | E69: 136 | F69: -3 | G69: =D69+F69-E69 -> -60 | H69: FY23: FY24 20-F cash flow statement (p.F-10). FY24-FY25: Q4-25 press release and FY25 20-F cash flow statement. H1 25 and H1 26: Q2-26 press release, six-month columns. LTM = FY25 + H1 26 - H1 25. Distorted by lending and deposit movements below; not used directly in the DCF.
A70: Purchase of PP&E | B70: -71 | C70: -77 | D70: -97 | E70: -24 | F70: -27 | G70: =D70+F70-E70 -> -100 | H70: Same sources as operating cash flow. Outflows shown as negatives.
A71: Purchase of intangibles | B71: -21 | C71: -36 | D71: -26 | E71: -14 | F71: -14 | G71: =D71+F71-E71 -> -26 | H71: Same sources as operating cash flow. Outflows shown as negatives.
A72: Cash capex | B72: =B70+B71 -> -92 | C72: =C70+C71 -> -113 | D72: =D70+D71 -> -123 | E72: =E70+E71 -> -38 | F72: =F70+F71 -> -41 | G72: =D72+F72-E72 -> -126 | H72: Formula: purchase of PP&E plus purchase of intangibles. Excludes assets acquired under lease arrangements.
A73: Proceeds from PP&E disposals | B73: 28 | C73: 26 | D73: 16 | E73: 5 | F73: 6 | G73: =D73+F73-E73 -> 17 | H73: Same sources as operating cash flow. Cash received from selling PP&E, so an inflow shown as a positive number (unlike the purchases above, which are negative). Added back in Grab’s capital expenditure definition
A74: Capex incl. leased assets | B74: -140 | C74: -149 | D74: -188 | E74: -60 | F74: -82 | G74: =D74+F74-E74 -> -210 | H74: Grab's capital expenditure definition in its Adjusted Free Cash Flow table; includes assets acquired using lease arrangements (vehicles). FY23: FY24 20-F Adjusted Free Cash Flow table. FY24-FY25 and H1: press releases. Use either this or cash capex consistently in the model, not both.
A75: Lease payments | B75: -39 | C75: -46 | D75: -52 | E75: -22 | F75: -32 | G75: =D75+F75-E75 -> -62 | H75: Same sources as operating cash flow. Outflows shown as negatives.
A76: Change in loan receivables | B76: -184 | C76: -276 | D76: -691 | E76: -158 | F76: -370 | G76: =D76+F76-E76 -> -903 | H76: Lending and bank-deposit movements from the cash flow statement. Included in operating cash flow, so they distort it. A negative loan figure means cash lent out; a positive deposit figure means cash received from customers
A77: Change in customer deposits | B77: 364 | C77: 843 | D77: 308 | E77: 229 | F77: 25 | G77: =D77+F77-E77 -> 104 | H77: Lending and bank-deposit movements from the cash flow statement. Included in operating cash flow, so they distort it. A negative loan figure means cash lent out; a positive deposit figure means cash received from customers
A78: Share buybacks | B78: 0 | C78: -226 | D78: -274 | E78: -274 | F78: -400 | G78: =D78+F78-E78 -> -400 | H78: Same sources as operating cash flow. Outflows shown as negatives.
A79: Memo: Adjusted free cash flow as reported | C79: 162 | D79: 290 | E79: 10 | F79: 171 | H79: Grab's non-IFRS measure as reported. Not comparable over time: from 2025 it includes PP&E disposal proceeds; from Q2 2026 it also excludes treasury liquidity movements in Financial Services. FY24 is the re-presented 162 (136 as originally reported). FY23 and LTM left blank for the same reason.
A80: AFCF Check | C80: =C69+C74+C73-C76-C77-C79 -> 0 | D80: =D69+D74+D73-D76-D77-D79 -> 0 | E80: =E69+E74+E73-E76-E77-E79 -> 0 | H80: Operating cash flow + capex incl. leased assets + disposal proceeds - loan receivables movement - deposit movement - reported AFCF. Should be 0. Not shown for H1 26 because of the Q2 2026 definition change (treasury liquidity, -95).
A82: Ratios
A83: Operating Margin | B83: =B13/B8 -> -0.22000848 | C83: =C13/C8 -> -0.060064355 | D83: =D13/D8 -> 0.019287834 | E83: =E13/E8 -> -0.0087939698 | F83: =F13/F8 -> 0.020993344 | G83: =G13/G8 -> 0.032162959
A84: Adjusted EBITDA Margin | B84: =B22/B8 -> -0.0093259856 | C84: =C22/C8 -> 0.11190561 | D84: =D22/D8 -> 0.14836795 | E84: =E22/E8 -> 0.13505025 | F84: =F22/F8 -> 0.16538658 | G84: =G22/G8 -> 0.16295899
A85: Share-based compensation % revenue | B85: =B16/B8 -> 0.12886816 | C85: =C16/C8 -> 0.099749732 | D85: =D16/D8 -> 0.071513353 | E85: =E16/E8 -> 0.088567839 | F85: =F16/F8 -> 0.071684588 | G85: =G16/G8 -> 0.064325918
A86: D&A % revenue | B86: =B15/B8 -> 0.061466723 | C86: =C15/C8 -> 0.05255631 | D86: =D15/D8 -> 0.052522255 | E86: =E15/E8 -> 0.050879397 | F86: =F15/F8 -> 0.055811572 | G86: =G15/G8 -> 0.054945055
A87: Capex incl. leased assets % revenue | B87: =-B74/B8 -> 0.059347181 | C87: =-C74/C8 -> 0.053271362 | D87: =-D74/D8 -> 0.05578635 | E87: =-E74/E8 -> 0.037688442 | F87: =-F74/F8 -> 0.041986687 | G87: =-G74/G8 -> 0.056285178
A89: Segment revenue growth
A90: Deliveries | C90: =C3/B3-1 -> 0.13969466 | D90: =D3/C3-1 -> 0.20562626 | F90: =F3/E3-1 -> 0.21896956
A91: Mobility | C91: =C4/B4-1 -> 0.20206659 | D91: =D4/C4-1 -> 0.16427889 | F91: =F4/E4-1 -> 0.15771231
A92: Financial services | C92: =C5/B5-1 -> 0.42937853 | D92: =D5/C5-1 -> 0.3715415 | F92: =F5/E5-1 -> 0.51572327

Sheet Forecast
A1: Grab DCF Forecast | M1: Notes
A2: ($m) | B2: FY25A | C2: FY26E | D2: FY27E | E2: FY28E | F2: FY29E | G2: FY30E | H2: FY31E | I2: FY32E | J2: FY33E | K2: FY34E | L2: FY35E
A3: Year (used later for discounting) | C3: 1 | D3: =C3+1 -> 2 | E3: =D3+1 -> 3 | F3: =E3+1 -> 4 | G3: =F3+1 -> 5 | H3: =G3+1 -> 6 | I3: =H3+1 -> 7 | J3: =I3+1 -> 8 | K3: =J3+1 -> 9 | L3: =K3+1 -> 10
A5: Assumptions
A6: Deliveries growth % | C6: 0.21 | D6: =C6+($L6-$C6)/9 -> 0.19222222 | E6: =D6+($L6-$C6)/9 -> 0.17444444 | F6: =E6+($L6-$C6)/9 -> 0.15666667 | G6: =F6+($L6-$C6)/9 -> 0.13888889 | H6: =G6+($L6-$C6)/9 -> 0.12111111 | I6: =H6+($L6-$C6)/9 -> 0.10333333 | J6: =I6+($L6-$C6)/9 -> 0.085555556 | K6: =J6+($L6-$C6)/9 -> 0.067777778 | L6: 0.05 | M6: FY26E 21%: H1 26 and Q2 26 run-rate (22% and 21%), consistent with guidance; fades to 5% by FY35E toward regional nominal GDP
A7: Mobility growth % | C7: 0.13 | D7: =C7+($L7-$C7)/9 -> 0.12111111 | E7: =D7+($L7-$C7)/9 -> 0.11222222 | F7: =E7+($L7-$C7)/9 -> 0.10333333 | G7: =F7+($L7-$C7)/9 -> 0.094444444 | H7: =G7+($L7-$C7)/9 -> 0.085555556 | I7: =H7+($L7-$C7)/9 -> 0.076666667 | J7: =I7+($L7-$C7)/9 -> 0.067777778 | K7: =J7+($L7-$C7)/9 -> 0.058888889 | L7: 0.05 | M7: FY26E 13%: between H1 26 (15.8%) and Q2 26 (12%) as Mobility slows; fades to 5%
A8: Financial services growth % | C8: 0.6 | D8: 0.3 | E8: =D8+($L8-$D8)/8 -> 0.26875 | F8: =E8+($L8-$D8)/8 -> 0.2375 | G8: =F8+($L8-$D8)/8 -> 0.20625 | H8: =G8+($L8-$D8)/8 -> 0.175 | I8: =H8+($L8-$D8)/8 -> 0.14375 | J8: =I8+($L8-$D8)/8 -> 0.1125 | K8: =J8+($L8-$D8)/8 -> 0.08125 | L8: 0.05 | M8: FY26E 60% includes Superbank and Stash consolidation, back-solved from guidance; FY27E 30% organic; fades to 5%
A9: Operating margin % (after share-based comp) | C9: 0.04 | D9: =C9+($L9-$C9)/9 -> 0.052222222 | E9: =D9+($L9-$C9)/9 -> 0.064444444 | F9: =E9+($L9-$C9)/9 -> 0.076666667 | G9: =F9+($L9-$C9)/9 -> 0.088888889 | H9: =G9+($L9-$C9)/9 -> 0.10111111 | I9: =H9+($L9-$C9)/9 -> 0.11333333 | J9: =I9+($L9-$C9)/9 -> 0.12555556 | K9: =J9+($L9-$C9)/9 -> 0.13777778 | L9: 0.15 | M9: FY26E 4.0%: guidance adjusted EBITDA less D&A, SBC and one-offs; FY35E 15%: management's 2028 target reached seven years later
A10: Tax rate | C10: 0.22 | M10: Blended statutory rate across Grab's markets (about 17%-25%); FY25 effective rate was about 26%
A11: D&A % of revenue | C11: 0.055 | M11: Held at the FY25 and LTM level of about 5.5% of revenue.
A12: Capex % of revenue (incl. leased assets) | C12: 0.056 | M12: Held at FY25 and LTM level of about 5.6%, including leased assets.
A13: Working capital investment % of revenue | C13: 0.005 | M13: Roughly zero historically; 0.5% is a cautious allowance for growth
A14: Share-based comp % of revenue (memo) | C14: 0.065 | M14: LTM was 6.4% and falling; memo for the adjusted EBITDA cross-check only.
A16: Revenue ($m)
A17: Deliveries | B17: =Historicals!D3 -> 1800 | C17: =B17*(1+C6) -> 2178 | D17: =C17*(1+D6) -> 2596.66 | E17: =D17*(1+E6) -> 3049.6329 | F17: =E17*(1+F6) -> 3527.4087 | G17: =F17*(1+G6) -> 4017.3266 | H17: =G17*(1+H6) -> 4503.8695 | I17: =H17*(1+I6) -> 4969.2694 | J17: =I17*(1+J6) -> 5394.418 | ... L17: =K17*(1+L6) -> 6048.0416
A18: Mobility | B18: =Historicals!D4 -> 1219 | C18: =B18*(1+C7) -> 1377.47 | D18: =C18*(1+D7) -> 1544.2969 | E18: =D18*(1+E7) -> 1717.6014 | F18: =E18*(1+F7) -> 1895.0868 | G18: =F18*(1+G7) -> 2074.0673 | H18: =G18*(1+H7) -> 2251.5152 | I18: =H18*(1+I7) -> 2424.1314 | J18: =I18*(1+J7) -> 2588.4336 | ... L18: =K18*(1+L7) -> 2877.9068
A19: Financial Services | B19: =Historicals!D5 -> 347 | C19: =B19*(1+C8) -> 555.2 | D19: =C19*(1+D8) -> 721.76 | E19: =D19*(1+E8) -> 915.733 | F19: =E19*(1+F8) -> 1133.2196 | G19: =F19*(1+G8) -> 1366.9461 | H19: =G19*(1+H8) -> 1606.1617 | I19: =H19*(1+I8) -> 1837.0474 | J19: =I19*(1+J8) -> 2043.7153 | ... L19: =K19*(1+L8) -> 2320.2555
A20: Others | B20: =Historicals!D6 -> 4 | C20: =B20 -> 4 | D20: =C20 -> 4 | E20: =D20 -> 4 | F20: =E20 -> 4 | G20: =F20 -> 4 | H20: =G20 -> 4 | I20: =H20 -> 4 | J20: =I20 -> 4 | ... L20: =K20 -> 4
A21: Total Revenue | B21: =SUM(B17:B20) -> 3370 | C21: =SUM(C17:C20) -> 4114.67 | D21: =SUM(D17:D20) -> 4866.7169 | E21: =SUM(E17:E20) -> 5686.9673 | F21: =SUM(F17:F20) -> 6559.7151 | G21: =SUM(G17:G20) -> 7462.34 | H21: =SUM(H17:H20) -> 8365.5464 | I21: =SUM(I17:I20) -> 9234.4482 | ... L21: =SUM(L17:L20) -> 11250.204
A22: Growth % | B22: =Historicals!D10 -> 0.20486235 | C22: =C21/B21-1 -> 0.22097033 | D22: =D21/C21-1 -> 0.18277211 | E22: =E21/D21-1 -> 0.16854285 | F22: =F21/E21-1 -> 0.15346455 | G22: =G21/F21-1 -> 0.13760123 | H22: =H21/G21-1 -> 0.12103528 | I22: =I21/H21-1 -> 0.10386671 | J22: =J21/I21-1 -> 0.08621183 | ... L22: =L21/K21-1 -> 0.049981334
A23: FY26 revenue guidance, midpoint ($m) | C23: 4125 | M23: Source: Grab Q2 2026 press release, 4 Aug 2026; FY26 revenue guidance $4.10bn to $4.15bn, midpoint
A24: Forecast vs guidance | C24: =C21/C23-1 -> -0.0025042424
A26: Free Cash Flow ($m)
A27: Operating profit (after SBC) | B27: =Historicals!D13 -> 65 | C27: =C21*C9 -> 164.5868 | D27: =D21*D9 -> 254.15077 | E27: =E21*E9 -> 366.49345 | F27: =F21*F9 -> 502.91149 | G27: =G21*G9 -> 663.31911 | H27: =H21*H9 -> 845.84969 | I27: =I21*I9 -> 1046.5708 | J27: =J21*J9 -> 1259.3934 | ... L27: =L21*L9 -> 1687.5306
A28: Tax | C28: =-MAX(C27,0)*$C$10 -> -36.209096 | D28: =-MAX(D27,0)*$C$10 -> -55.91317 | E28: =-MAX(E27,0)*$C$10 -> -80.628558 | F28: =-MAX(F27,0)*$C$10 -> -110.64053 | G28: =-MAX(G27,0)*$C$10 -> -145.9302 | H28: =-MAX(H27,0)*$C$10 -> -186.08693 | I28: =-MAX(I27,0)*$C$10 -> -230.24557 | J28: =-MAX(J27,0)*$C$10 -> -277.06655 | ... L28: =-MAX(L27,0)*$C$10 -> -371.25673
A29: Operating profit after tax | C29: =C27+C28 -> 128.3777 | D29: =D27+D28 -> 198.2376 | E29: =E27+E28 -> 285.86489 | F29: =F27+F28 -> 392.27097 | G29: =G27+G28 -> 517.38891 | H29: =H27+H28 -> 659.76276 | I29: =I27+I28 -> 816.32522 | J29: =J27+J28 -> 982.32685 | ... L29: =L27+L28 -> 1316.2739
A30: +D&A | B30: =Historicals!D15 -> 177 | C30: =C21*$C$11 -> 226.30685 | D30: =D21*$C$11 -> 267.66943 | E30: =E21*$C$11 -> 312.7832 | F30: =F21*$C$11 -> 360.78433 | G30: =G21*$C$11 -> 410.4287 | H30: =H21*$C$11 -> 460.10505 | I30: =I21*$C$11 -> 507.89465 | J30: =J21*$C$11 -> 551.68118 | ... L30: =L21*$C$11 -> 618.76121
A31: - Capex | B31: =Historicals!D74 -> -188 | C31: =-C21*$C$12 -> -230.42152 | D31: =-D21*$C$12 -> -272.53615 | E31: =-E21*$C$12 -> -318.47017 | F31: =-F21*$C$12 -> -367.34405 | G31: =-G21*$C$12 -> -417.89104 | H31: =-H21*$C$12 -> -468.4706 | I31: =-I21*$C$12 -> -517.1291 | J31: =-J21*$C$12 -> -561.71174 | ... L31: =-L21*$C$12 -> -630.01142
A32: - Working Capital | C32: =-C21*$C$13 -> -20.57335 | D32: =-D21*$C$13 -> -24.333585 | E32: =-E21*$C$13 -> -28.434836 | F32: =-F21*$C$13 -> -32.798576 | G32: =-G21*$C$13 -> -37.3117 | H32: =-H21*$C$13 -> -41.827732 | I32: =-I21*$C$13 -> -46.172241 | J32: =-J21*$C$13 -> -50.152834 | ... L32: =-L21*$C$13 -> -56.251019
A33: Free cash flow | C33: =C29+C30+C31+C32 -> 103.68968 | D33: =D29+D30+D31+D32 -> 169.0373 | E33: =E29+E30+E31+E32 -> 251.74308 | F33: =F29+F30+F31+F32 -> 352.91268 | G33: =G29+G30+G31+G32 -> 472.61487 | H33: =H29+H30+H31+H32 -> 609.56948 | I33: =I29+I30+I31+I32 -> 760.91853 | J33: =J29+J30+J31+J32 -> 922.14345 | ... L33: =L29+L30+L31+L32 -> 1248.7726
A34: FCF % of revenue | C34: =C33/C21 -> 0.0252 | D34: =D33/D21 -> 0.034733333 | E34: =E33/E21 -> 0.044266667 | F34: =F33/F21 -> 0.0538 | G34: =G33/G21 -> 0.063333333 | H34: =H33/H21 -> 0.072866667 | I34: =I33/I21 -> 0.0824 | J34: =J33/J21 -> 0.091933333 | ... L34: =L33/L21 -> 0.111
A36: Cross-check
A37: Implied adjusted EBITDA | B37: =Historicals!D22 -> 500 | C37: =C27+C30+C21*$C$14 -> 658.3472 | D37: =D27+D30+D21*$C$14 -> 838.1568 | E37: =E27+E30+E21*$C$14 -> 1048.9295 | F37: =F27+F30+F21*$C$14 -> 1290.0773 | G37: =G27+G30+G21*$C$14 -> 1558.7999 | H37: =H27+H30+H21*$C$14 -> 1849.7153 | I37: =I27+I30+I21*$C$14 -> 2154.7046 | J37: =J27+J30+J21*$C$14 -> 2463.0614 | ... L37: =L27+L30+L21*$C$14 -> 3037.5551
A38: Implied adjusted EBITDA margin | B38: =B37/B21 -> 0.14836795 | C38: =C37/C21 -> 0.16 | D38: =D37/D21 -> 0.17222222 | E38: =E37/E21 -> 0.18444444 | F38: =F37/F21 -> 0.19666667 | G38: =G37/G21 -> 0.20888889 | H38: =H37/H21 -> 0.22111111 | I38: =I37/I21 -> 0.23333333 | ... L38: =L37/L21 -> 0.27

Sheet WACC
A1: WACC
A4: Risk-free rate | B4: 0.0531 | C4: 10-year US Treasury constant maturity yield, 5 Oct 2026, 5.31% (FRED DGS10 / Federal Reserve H.15). Market close on 6 Oct was about 5.27%
A5: Equity risk premium (mature market) | B5: 0.0423 | C5: Damodaran's January 2026 mature-market equity risk premium
A6: Country risk premium (SEA) | B6: 0.0172 | C6: FY25 revenue by country (FY25 20-F) times Damodaran's January 2026 country premiums, with Rest of SEA (0.9% of revenue) excluded
A7: Beta | B7: 1.3 | C7: Bottom-up beta, not Grab's own regression beta. Damodaran Jan 2026 global Software (Internet): levered 1.39, unlevered 1.30 (1.34 ex-cash). Rounded to 1.3 and not relevered upward because Grab holds net cash (gross cash liquidity about $7.4bn vs borrowings about $2.0bn). Observed 5-year monthly regression beta of 0.91 (Yahoo Finance) rejected: under 60 observations since the late-2021 listing and unstable across providers (0.83 to 1.40).
A8: Cost of equity | B8: =B4+B7*B5+B6 -> 0.12529
A9: Credit spread over risk-free rate | B9: 0.02
A10: Pre-tax cost of debt | B10: =B4+B9 -> 0.0731 | C10: Risk-free rate plus 2.0% credit spread (estimate; Grab's rating not verified). Grab's stated borrowing rates (bank loans about 2.6% weighted, leases 3.6% to 12.5%) are in local currencies and the $1.5bn convertible is zero coupon, so they understate a USD cost of debt. Source: FY25 20-F, loans and borrowings note
A11: Tax rate | B11: =Forecast!C10 -> 0.22
A12: After-tax cost of debt | B12: =B10*(1-B11) -> 0.057018
A14: share price ($) | B14: 3.07 | C14: Grab Holdings Ltd (GRAB) closing price on 6th October
A15: Equity value ($m) | B15: =B14*Historicals!E59 -> 12522.53 | C15: Share price (B14) x total shares outstanding at 30 June 2026 of 4,079m (Class A 3,974m + Class B 105m), from the Q2 2026 press release (4 Aug 2026); see Historicals row 59. Basic shares only: options, RSUs and the convertible notes are not included. The $351m ASR and forward share purchases were fully completed in July 2026, so the true count is slightly lower.
A16: Debt ($m) | B16: =Historicals!E46 -> 2033 | C16: Total loans and borrowings at 30 June 2026: non-current 409 + current 1,624 = 2,033 ($m), from the statement of financial position in the Q2 2026 press release; see Historicals row 46. Includes lease liabilities, bank loans and the $1.5bn zero-coupon convertible notes due 2030 (carried at about 1,502 at Dec-25, including the embedded conversion option). Excludes customer deposits in the banking business (2,513), which fund the lending business, not Grab's operations.
A17: E/(D+E) | B17: =B15/(B15+B16) -> 0.860328
A18: D/(D+E) | B18: =B16/(B15+B16) -> 0.139672
A19: WACC | B19: =B17*B8+B18*B12 -> 0.11575431

Sheet DCF
A2: ($m) | C2: =Forecast!C2 -> FY26E | D2: =Forecast!D2 -> FY27E | E2: =Forecast!E2 -> FY28E | F2: =Forecast!F2 -> FY29E | G2: =Forecast!G2 -> FY30E | H2: =Forecast!H2 -> FY31E | I2: =Forecast!I2 -> FY32E | J2: =Forecast!J2 -> FY33E | ... L2: =Forecast!L2 -> FY35E
A3: Year | C3: =Forecast!C3 -> 1 | D3: =Forecast!D3 -> 2 | E3: =Forecast!E3 -> 3 | F3: =Forecast!F3 -> 4 | G3: =Forecast!G3 -> 5 | H3: =Forecast!H3 -> 6 | I3: =Forecast!I3 -> 7 | J3: =Forecast!J3 -> 8 | ... L3: =Forecast!L3 -> 10
A5: Free cash flow | C5: =Forecast!C33 -> 103.68968 | D5: =Forecast!D33 -> 169.0373 | E5: =Forecast!E33 -> 251.74308 | F5: =Forecast!F33 -> 352.91268 | G5: =Forecast!G33 -> 472.61487 | H5: =Forecast!H33 -> 609.56948 | I5: =Forecast!I33 -> 760.91853 | J5: =Forecast!J33 -> 922.14345 | ... L5: =Forecast!L33 -> 1248.7726
A6: Discount factor | C6: =1/(1+WACC!$B$19)^C3 -> 0.89625466 | D6: =1/(1+WACC!$B$19)^D3 -> 0.80327241 | E6: =1/(1+WACC!$B$19)^E3 -> 0.71993664 | F6: =1/(1+WACC!$B$19)^F3 -> 0.64524657 | G6: =1/(1+WACC!$B$19)^G3 -> 0.57830524 | H6: =1/(1+WACC!$B$19)^H3 -> 0.51830877 | I6: =1/(1+WACC!$B$19)^I3 -> 0.46453665 | J6: =1/(1+WACC!$B$19)^J3 -> 0.41634313 | ... L6: =1/(1+WACC!$B$19)^L3 -> 0.33443695
A7: Present value of free cash flow | C7: =C5*C6 -> 92.932362 | D7: =D5*D6 -> 135.783 | E7: =E5*E6 -> 181.23907 | F7: =F5*F6 -> 227.71569 | G7: =G5*G6 -> 273.31565 | H7: =H5*H6 -> 315.94521 | I7: =I5*I6 -> 353.47454 | J7: =J5*J6 -> 383.92809 | ... L7: =L5*L6 -> 417.63571
A9: Sum of PV of FCF | B9: =SUM(C7:L7) -> 2787.6507
A10: Terminal growth rate | B10: 0.025
A11: FY35E FCF grown one year | B11: =L5*(1+B10) -> 1279.9919
A12: Terminal value | B12: =B11/(WACC!B19-B10) -> 14103.924
A13: PV of terminal value | B13: =B12*L6 -> 4716.8734
A14: Enterprise value | B14: =B9+B13 -> 7504.5241
A15: Terminal value as % of enterprise value | B15: =B13/B14 -> 0.62853731
A17: Bridge to value per share ($m)
A18: Enterprise value | B18: =B14 -> 7504.5241
A19: Add: Gross cash liquidity | B19: =Historicals!E52*1000 -> 7400 | C19: Reported gross cash liquidity, Jun-26 ($7.4bn); includes cash that backs customer deposits
A20: Less: Customer deposits (banking) | B20: =-Historicals!E43 -> -2513 | C20: Deducted because deposits fund the banking business and the lending, and the cash behind them isn’t Grab’s.
A21: Less: Loans & borrowings (incl. convertibles, leases) | B21: =-Historicals!E46 -> -2033 | C21: Includes the $1.5bn zero-coupon convertible notes (treated as debt: share price far below the ~$6.55 conversion price) and lease liabilities
A22: Less: Non-controlling interests | B22: =-Historicals!E44 -> -437 | C22: Book value at Jun-26; mostly Superbank minorities. A rough proxy for their share of value
A23: Equity value | B23: =SUM(B18:B22) -> 9921.5241
A24: Diluted shares (m) | B24: 4168 | C24: Q2 2026 diluted weighted-average shares (press release); an approximation, as July buybacks aren’t fully reflected
A25: Value per share ($) | B25: =B23/B24 -> 2.380404
A26: Current share price ($) | B26: =WACC!B14 -> 3.07
A27: Upside/(downside) | B27: =B25/B26-1 -> -0.22462409

Sheet Sensitivity
A1: Value per share ($) – sensitivity to WACC and terminal growth | B1: WACC →, Terminal growth ↓
A2: =DCF!B25 -> 2.380404 | B2: 0.105 | C2: 0.11 | D2: =WACC!B19 -> 0.11575431 | E2: 0.12 | F2: 0.125
A3: 0.015 | B3: {=(SUMPRODUCT(DCF!$C$5:$L$5/(1+B$2)^DCF!$C$3:$L$3)+DCF!$L$5*(1+$A3)/(B$2-$A3)/(1+B$2)^DCF!$L$3+SUM(DCF!$B$19:$B$22))/DCF!$B$24} -> 2.5381885 | C3: {=(SUMPRODUCT(DCF!$C$5:$L$5/(1+C$2)^DCF!$C$3:$L$3)+DCF!$L$5*(1+$A3)/(C$2-$A3)/(1+C$2)^DCF!$L$3+SUM(DCF!$B$19:$B$22))/DCF!$B$24} -> 2.3994429 | D3: {=(SUMPRODUCT(DCF!$C$5:$L$5/(1+D$2)^DCF!$C$3:$L$3)+DCF!$L$5*(1+$A3)/(D$2-$A3)/(1+D$2)^DCF!$L$3+SUM(DCF!$B$19:$B$22))/DCF!$B$24} -> 2.2581375 | E3: {=(SUMPRODUCT(DCF!$C$5:$L$5/(1+E$2)^DCF!$C$3:$L$3)+DCF!$L$5*(1+$A3)/(E$2-$A3)/(1+E$2)^DCF!$L$3+SUM(DCF!$B$19:$B$22))/DCF!$B$24} -> 2.1646483 | F3: {=(SUMPRODUCT(DCF!$C$5:$L$5/(1+F$2)^DCF!$C$3:$L$3)+DCF!$L$5*(1+$A3)/(F$2-$A3)/(1+F$2)^DCF!$L$3+SUM(DCF!$B$19:$B$22))/DCF!$B$24} -> 2.0646427
A4: 0.02 | B4: {=(SUMPRODUCT(DCF!$C$5:$L$5/(1+B$2)^DCF!$C$3:$L$3)+DCF!$L$5*(1+$A4)/(B$2-$A4)/(1+B$2)^DCF!$L$3+SUM(DCF!$B$19:$B$22))/DCF!$B$24} -> 2.6179152 | C4: {=(SUMPRODUCT(DCF!$C$5:$L$5/(1+C$2)^DCF!$C$3:$L$3)+DCF!$L$5*(1+$A4)/(C$2-$A4)/(1+C$2)^DCF!$L$3+SUM(DCF!$B$19:$B$22))/DCF!$B$24} -> 2.467937 | D4: {=(SUMPRODUCT(DCF!$C$5:$L$5/(1+D$2)^DCF!$C$3:$L$3)+DCF!$L$5*(1+$A4)/(D$2-$A4)/(1+D$2)^DCF!$L$3+SUM(DCF!$B$19:$B$22))/DCF!$B$24} -> 2.3160786 | E4: {=(SUMPRODUCT(DCF!$C$5:$L$5/(1+E$2)^DCF!$C$3:$L$3)+DCF!$L$5*(1+$A4)/(E$2-$A4)/(1+E$2)^DCF!$L$3+SUM(DCF!$B$19:$B$22))/DCF!$B$24} -> 2.216097 | F4: {=(SUMPRODUCT(DCF!$C$5:$L$5/(1+F$2)^DCF!$C$3:$L$3)+DCF!$L$5*(1+$A4)/(F$2-$A4)/(1+F$2)^DCF!$L$3+SUM(DCF!$B$19:$B$22))/DCF!$B$24} -> 2.1095763
A5: =DCF!B10 -> 0.025 | B5: {=(SUMPRODUCT(DCF!$C$5:$L$5/(1+B$2)^DCF!$C$3:$L$3)+DCF!$L$5*(1+$A5)/(B$2-$A5)/(1+B$2)^DCF!$L$3+SUM(DCF!$B$19:$B$22))/DCF!$B$24} -> 2.7076077 | C5: {=(SUMPRODUCT(DCF!$C$5:$L$5/(1+C$2)^DCF!$C$3:$L$3)+DCF!$L$5*(1+$A5)/(C$2-$A5)/(1+C$2)^DCF!$L$3+SUM(DCF!$B$19:$B$22))/DCF!$B$24} -> 2.5444891 | D5: {=(SUMPRODUCT(DCF!$C$5:$L$5/(1+D$2)^DCF!$C$3:$L$3)+DCF!$L$5*(1+$A5)/(D$2-$A5)/(1+D$2)^DCF!$L$3+SUM(DCF!$B$19:$B$22))/DCF!$B$24} -> 2.380404 | E5: {=(SUMPRODUCT(DCF!$C$5:$L$5/(1+E$2)^DCF!$C$3:$L$3)+DCF!$L$5*(1+$A5)/(E$2-$A5)/(1+E$2)^DCF!$L$3+SUM(DCF!$B$19:$B$22))/DCF!$B$24} -> 2.2729613 | F5: {=(SUMPRODUCT(DCF!$C$5:$L$5/(1+F$2)^DCF!$C$3:$L$3)+DCF!$L$5*(1+$A5)/(F$2-$A5)/(1+F$2)^DCF!$L$3+SUM(DCF!$B$19:$B$22))/DCF!$B$24} -> 2.1590033
A6: 0.03 | B6: {=(SUMPRODUCT(DCF!$C$5:$L$5/(1+B$2)^DCF!$C$3:$L$3)+DCF!$L$5*(1+$A6)/(B$2-$A6)/(1+B$2)^DCF!$L$3+SUM(DCF!$B$19:$B$22))/DCF!$B$24} -> 2.8092593 | C6: {=(SUMPRODUCT(DCF!$C$5:$L$5/(1+C$2)^DCF!$C$3:$L$3)+DCF!$L$5*(1+$A6)/(C$2-$A6)/(1+C$2)^DCF!$L$3+SUM(DCF!$B$19:$B$22))/DCF!$B$24} -> 2.6306103 | D6: {=(SUMPRODUCT(DCF!$C$5:$L$5/(1+D$2)^DCF!$C$3:$L$3)+DCF!$L$5*(1+$A6)/(D$2-$A6)/(1+D$2)^DCF!$L$3+SUM(DCF!$B$19:$B$22))/DCF!$B$24} -> 2.4522306 | E6: {=(SUMPRODUCT(DCF!$C$5:$L$5/(1+E$2)^DCF!$C$3:$L$3)+DCF!$L$5*(1+$A6)/(E$2-$A6)/(1+E$2)^DCF!$L$3+SUM(DCF!$B$19:$B$22))/DCF!$B$24} -> 2.3361439 | F6: {=(SUMPRODUCT(DCF!$C$5:$L$5/(1+F$2)^DCF!$C$3:$L$3)+DCF!$L$5*(1+$A6)/(F$2-$A6)/(1+F$2)^DCF!$L$3+SUM(DCF!$B$19:$B$22))/DCF!$B$24} -> 2.213633
A7: 0.035 | B7: {=(SUMPRODUCT(DCF!$C$5:$L$5/(1+B$2)^DCF!$C$3:$L$3)+DCF!$L$5*(1+$A7)/(B$2-$A7)/(1+B$2)^DCF!$L$3+SUM(DCF!$B$19:$B$22))/DCF!$B$24} -> 2.9254324 | C7: {=(SUMPRODUCT(DCF!$C$5:$L$5/(1+C$2)^DCF!$C$3:$L$3)+DCF!$L$5*(1+$A7)/(C$2-$A7)/(1+C$2)^DCF!$L$3+SUM(DCF!$B$19:$B$22))/DCF!$B$24} -> 2.7282143 | D7: {=(SUMPRODUCT(DCF!$C$5:$L$5/(1+D$2)^DCF!$C$3:$L$3)+DCF!$L$5*(1+$A7)/(D$2-$A7)/(1+D$2)^DCF!$L$3+SUM(DCF!$B$19:$B$22))/DCF!$B$24} -> 2.5329517 | E7: {=(SUMPRODUCT(DCF!$C$5:$L$5/(1+E$2)^DCF!$C$3:$L$3)+DCF!$L$5*(1+$A7)/(E$2-$A7)/(1+E$2)^DCF!$L$3+SUM(DCF!$B$19:$B$22))/DCF!$B$24} -> 2.4067597 | F7: {=(SUMPRODUCT(DCF!$C$5:$L$5/(1+F$2)^DCF!$C$3:$L$3)+DCF!$L$5*(1+$A7)/(F$2-$A7)/(1+F$2)^DCF!$L$3+SUM(DCF!$B$19:$B$22))/DCF!$B$24} -> 2.2743328
A8: Current share price: $3.07 - No cell reaches the current price; the highest is $2.93
